eazyrent/.openapi-generator/FILES
eazyrent/.openapi-generator/VERSION
eazyrent/.openapi-generator-ignore
eazyrent/__init__.py
eazyrent/api.py
eazyrent/core/__init__.py
eazyrent/core/v1/__init__.py
eazyrent/core/v1/api/__init__.py
eazyrent/core/v1/api/accepted_supporting_documents_api.py
eazyrent/core/v1/api/applicant_files_api.py
eazyrent/core/v1/api/applicants_api.py
eazyrent/core/v1/api/physical_guarantors_api.py
eazyrent/core/v1/api/rents_api.py
eazyrent/core/v1/api/supporting_documents_api.py
eazyrent/core/v1/api/users_api.py
eazyrent/core/v1/api_client.py
eazyrent/core/v1/api_response.py
eazyrent/core/v1/configuration.py
eazyrent/core/v1/docs/AcceptedSupportingDocument.md
eazyrent/core/v1/docs/AcceptedSupportingDocumentsApi.md
eazyrent/core/v1/docs/AlertPretty.md
eazyrent/core/v1/docs/ApisCoreSchemasV1ApplicantsPhysicalGuarantor.md
eazyrent/core/v1/docs/ApisCoreSchemasV1PhysicalGuarantorsPhysicalGuarantor.md
eazyrent/core/v1/docs/Applicant.md
eazyrent/core/v1/docs/ApplicantFilesApi.md
eazyrent/core/v1/docs/ApplicantLight.md
eazyrent/core/v1/docs/ApplicantList.md
eazyrent/core/v1/docs/ApplicantsApi.md
eazyrent/core/v1/docs/ApplicantsSituationEnum.md
eazyrent/core/v1/docs/Company.md
eazyrent/core/v1/docs/CompanyConfig.md
eazyrent/core/v1/docs/CreateApplicant.md
eazyrent/core/v1/docs/FormatEnum.md
eazyrent/core/v1/docs/HTTPValidationError.md
eazyrent/core/v1/docs/Id.md
eazyrent/core/v1/docs/LightUploadFile.md
eazyrent/core/v1/docs/Next.md
eazyrent/core/v1/docs/PaginatedResponseAcceptedSupportingDocument.md
eazyrent/core/v1/docs/PaginatedResponseApplicantList.md
eazyrent/core/v1/docs/PaginatedResponsePhysicalGuarantor.md
eazyrent/core/v1/docs/PaginatedResponsePropertyRentList.md
eazyrent/core/v1/docs/PaginatedResponseRentalFileFull.md
eazyrent/core/v1/docs/PaginatedResponseRentalFileList.md
eazyrent/core/v1/docs/PaginatedResponseSupportingDocumentList.md
eazyrent/core/v1/docs/PhysicalGuarantorCreate.md
eazyrent/core/v1/docs/PhysicalGuarantorsApi.md
eazyrent-0.3.0.dist-info/LICENSE.md
eazyrent-0.3.0.dist-info/METADATA
eazyrent-0.3.0.dist-info/WHEEL
eazyrent-0.3.0.dist-info/RECORD
