Metadata-Version: 2.3
Name: eazyrent
Version: 0.3.0
Summary: Software development kit for Eazyrent
License: Apache 2.0
Author: Thibault GRANDJEAN
Author-email: thibault@eazyrent.fr
Requires-Python: >=3.10,<4.0
Classifier: Development Status :: 1 - Planning
Classifier: License :: Other/Proprietary License
Classifier: Natural Language :: English
Classifier: Operating System :: OS Independent
Classifier: Programming Language :: Python
Classifier: Programming Language :: Python :: 3
Classifier: Programming Language :: Python :: 3.10
Classifier: Programming Language :: Python :: 3.11
Classifier: Programming Language :: Python :: 3.12
Classifier: Programming Language :: Python :: 3.13
Requires-Dist: levenshtein
Requires-Dist: minilog
Requires-Dist: pydantic[email] (>=2)
Requires-Dist: pyjwt[crypto]
Requires-Dist: python-dateutil (>=2.8.2)
Requires-Dist: typing-extensions (>=4.7.1)
Requires-Dist: urllib3 (<3.0.0)
Project-URL: Documentation, https://eazyrent_sdk.readthedocs.io
Project-URL: Homepage, https://pypi.org/project/eazyrent_sdk
Project-URL: Repository, https://gitlab.com/e3146/eazyrent/sdks/python-sdk
